Metadata-Version: 2.1
Name: odoo-addon-shopinvader_sale_cart_anonymous_partner
Version: 16.0.1.0.1
Summary: Glue module between shopinvader_sale_cart and shopinvader_anonymous_partner. This module solves cart conflicts when an anonymous user sign in.
Home-page: https://github.com/shopinvader/odoo-shopinvader
Author: Akretion
License: AGPL-3
Classifier: Programming Language :: Python
Classifier: Framework :: Odoo
Classifier: Framework :: Odoo :: 16.0
Classifier: License :: OSI Approved :: GNU Affero General Public License v3
Requires-Python: >=3.10
Requires-Dist: odoo-addon-shopinvader-anonymous-partner<16.1dev,>=16.0dev
Requires-Dist: odoo-addon-shopinvader-sale-cart<16.1dev,>=16.0dev
Requires-Dist: odoo<16.1dev,>=16.0a
